{
	"name": "CCGRCG65",
	"numInputs": "9",
	"numOutputs": "6",
	"maxLevel": "30",
	"numEdges": "1434",
	"reliability": "0.98632812500000000000",
	"size": "0.00000000000000000000",
	"area": "0.00000000000000000000",
	"longest_path": "0",
	"gates": "0",
	"sensitivity_factor": "0.00000000000000000000",
	"sinsitivity_factor_percent": "0.00000000000000000000",
	"sensitive_area": "0.00000000000000000000",
	"sensitive_area_percent": "0.00000000000000000000",
	"hash_code": "",
	"numElementsOfEachType": {
		"and": 106,
		"buf": 108,
		"input": 9,
		"nand": 110,
		"nor": 115,
		"not": 88,
		"or": 106,
		"output": 6,
		"xnor": 103,
		"xor": 97
	},
	"numEdgesOfEachType": {
		"and-and": 23,
		"and-buf": 17,
		"and-nand": 26,
		"and-nor": 36,
		"and-not": 8,
		"and-or": 26,
		"and-xnor": 31,
		"and-xor": 21,
		"buf-and": 34,
		"buf-buf": 14,
		"buf-nand": 17,
		"buf-nor": 27,
		"buf-not": 8,
		"buf-or": 33,
		"buf-xnor": 33,
		"buf-xor": 19,
		"input-and": 9,
		"input-buf": 7,
		"input-nand": 10,
		"input-nor": 10,
		"input-not": 7,
		"input-or": 12,
		"input-xnor": 8,
		"input-xor": 9,
		"nand-and": 29,
		"nand-buf": 16,
		"nand-nand": 20,
		"nand-nor": 23,
		"nand-not": 9,
		"nand-or": 24,
		"nand-xnor": 28,
		"nand-xor": 24,
		"nor-and": 20,
		"nor-buf": 13,
		"nor-nand": 24,
		"nor-nor": 37,
		"nor-not": 13,
		"nor-or": 30,
		"nor-xnor": 17,
		"nor-xor": 25,
		"not-and": 27,
		"not-buf": 10,
		"not-nand": 21,
		"not-nor": 20,
		"not-not": 8,
		"not-or": 25,
		"not-xnor": 18,
		"not-xor": 22,
		"or-and": 22,
		"or-buf": 11,
		"or-nand": 38,
		"or-nor": 22,
		"or-not": 8,
		"or-or": 19,
		"or-output": 4,
		"or-xnor": 22,
		"or-xor": 23,
		"xnor-and": 23,
		"xnor-buf": 9,
		"xnor-nand": 30,
		"xnor-nor": 26,
		"xnor-not": 13,
		"xnor-or": 17,
		"xnor-output": 2,
		"xnor-xnor": 25,
		"xnor-xor": 27,
		"xor-and": 19,
		"xor-buf": 11,
		"xor-nand": 27,
		"xor-nor": 20,
		"xor-not": 14,
		"xor-or": 19,
		"xor-xnor": 18,
		"xor-xor": 17
	},
	"abcStats": {
		"area": 1728.49,
		"delay": 2422.66,
		"edge": 805,
		"fileRead": true,
		"inputs": 9,
		"inputsNumberCorrect": true,
		"lat": 0,
		"lev": 28,
		"nd": 316,
		"outputs": 6,
		"outputsNumberCorrect": true
	},
	"abcStatsBalance": {
		"area": 1159.31,
		"delay": 2087.89,
		"edge": 559,
		"fileRead": true,
		"inputs": 9,
		"lat": 0,
		"lev": 24,
		"nd": 223,
		"outputs": 6
	},
	"abcStatsResyn2": {
		"area": 1031.80,
		"delay": 2005.57,
		"edge": 481,
		"fileRead": true,
		"inputs": 9,
		"lat": 0,
		"lev": 22,
		"nd": 195,
		"outputs": 6
	}
}